{
  "total_violation_records": 17172,
  "violation_columns": [
    "case_no",
    "ap_case_defn_key",
    "status_dttm",
    "status",
    "code",
    "value",
    "description",
    "violation_stno",
    "violation_sthigh",
    "violation_street",
    "violation_suffix",
    "violation_city",
    "violation_state",
    "violation_zip",
    "ward",
    "contact_addr1",
    "contact_addr2",
    "contact_city",
    "contact_state",
    "contact_zip",
    "sam_id",
    "latitude",
    "longitude",
    "location"
  ],
  "date_min": "2009-12-01 13:18:47",
  "date_max": "2026-03-20 15:27:46",
  "missing_status_dttm": 1,
  "duplicate_case_no_groups": 125,
  "unique_codes": 520,
  "raw_violations_path": "D:\\Projects\\CS506Project\\data\\raw\\violations.csv",
  "population_source_available": true,
  "population_lookup_path": "D:\\Projects\\CS506Project\\data\\external\\neighborhood_population.csv",
  "property_assessment_source_available": true,
  "structural_feature_table_available": true,
  "code_dictionary_available": true
}